privileged_residues/__init__.py
privileged_residues/chemical.py
privileged_residues/geometry.py
privileged_residues/postproc.py
privileged_residues/privileged_residues.py
privileged_residues/table.py
privileged_residues/util.py
privileged_residues/data/functional_groups/amine.params
privileged_residues/data/functional_groups/carboxamide.params
privileged_residues/data/functional_groups/carboxylate.params
privileged_residues/data/functional_groups/guanidinium.params
privileged_residues/data/functional_groups/hydroxide.params
privileged_residues/data/functional_groups/imidazole.params
privileged_residues/data/functional_groups/imidazole_D.params
privileged_residues-0.5.0.dist-info/METADATA
privileged_residues-0.5.0.dist-info/RECORD
privileged_residues-0.5.0.dist-info/WHEEL
privileged_residues-0.5.0.dist-info/top_level.txt
