Metadata-Version: 2.1
Name: privileged-residues
Version: 0.5.0
Summary: Privileged Residues contains methods for placing residues on the surface of a target protein that can be added to a RIF.
Home-page: https://github.com/RosettaCommons/privileged_residues
Author: Brian D. Weitzner
Author-email: weitzner@uw.edu
License: Apache Software License 2.0
Keywords: privileged_residues
Platform: UNKNOWN
Classifier: Development Status :: 2 - Pre-Alpha
Classifier: Intended Audience :: Developers
Classifier: License :: OSI Approved :: Apache Software License
Classifier: Natural Language :: English
Classifier: Programming Language :: Python :: 3
Classifier: Programming Language :: Python :: 3.5
Classifier: Programming Language :: Python :: 3.6
Requires-Dist: Click (>=6.0)
Requires-Dist: more-itertools
